{"created_at":"Sat Jun 04 20:21:01 +0000 2016","id":739190240749989888,"id_str":"739190240749989888","text":"Dass mir grad der #oidapolzer als erster auff\u00e4llt, der mich blockiert hat #autned","source":"\u003ca href=\"http:\/\/twitter.com\/download\/android\" rel=\"nofollow\"\u003eTwitter for Android\u003c\/a\u003e","truncated":false,"in_reply_to_status_id":739189383878807554,"in_reply_to_status_id_str":"739189383878807554","in_reply_to_user_id":2171045919,"in_reply_to_user_id_str":"2171045919","in_reply_to_screen_name":"mlang1994","user":{"id":2171045919,"id_str":"2171045919","name":"Matthias Lang","screen_name":"mlang1994","location":"Wien, Eisenstadt, Steinberg","url":"http:\/\/mattlang94.wordpress.com","description":"Wird BIM || Ex-Praktikant bei http:\/\/wien.ORF.at || Lassen Sie mich Journalist, ich bin durch","protected":false,"verified":false,"followers_count":278,"friends_count":304,"listed_count":12,"favourites_count":2447,"statuses_count":4261,"created_at":"Wed Nov 06 17:02:29 +0000 2013","utc_offset":7200,"time_zone":"Vienna","geo_enabled":false,"lang":"de","contributors_enabled":false,"is_translator":false,"profile_background_color":"94D487","profile_background_image_url":"http:\/\/abs.twimg.com\/images\/themes\/theme12\/bg.gif","profile_background_image_url_https":"https:\/\/abs.twimg.com\/images\/themes\/theme12\/bg.gif","profile_background_tile":false,"profile_link_color":"4A913C","profile_sidebar_border_color":"F2E195","profile_sidebar_fill_color":"FFF7CC","profile_text_color":"0C3E53","profile_use_background_image":true,"profile_image_url":"http:\/\/pbs.twimg.com\/profile_images\/707675506863243264\/lyFmLF0t_normal.jpg","profile_image_url_https":"https:\/\/pbs.twimg.com\/profile_images\/707675506863243264\/lyFmLF0t_normal.jpg","profile_banner_url":"https:\/\/pbs.twimg.com\/profile_banners\/2171045919\/1457557872","default_profile":false,"default_profile_image":false,"following":null,"follow_request_sent":null,"notifications":null},"geo":null,"coordinates":null,"place":null,"contributors":null,"is_quote_status":false,"retweet_count":0,"favorite_count":0,"entities":{"hashtags":[{"text":"oidapolzer","indices":[18,29]},{"text":"autned","indices":[74,81]}],"urls":[],"user_mentions":[],"symbols":[]},"favorited":false,"retweeted":false,"filter_level":"low","lang":"de","timestamp_ms":"1465071661542"}
{"created_at":"Sat Jun 04 20:21:03 +0000 2016","id":739190249553821697,"id_str":"739190249553821697","text":"RT @ChrisNeuhold: Wie hei\u00dft es so sch\u00f6n:Verpatzte Generalprobe, gelungene Premiere. #autned","source":"\u003ca href=\"http:\/\/twitter.com\/download\/android\" rel=\"nofollow\"\u003eTwitter for Android\u003c\/a\u003e","truncated":false,"in_reply_to_status_id":null,"in_reply_to_status_id_str":null,"in_reply_to_user_id":null,"in_reply_to_user_id_str":null,"in_reply_to_screen_name":null,"user":{"id":4106871880,"id_str":"4106871880","name":"Markus Peer","screen_name":"baerli002","location":null,"url":null,"description":null,"protected":false,"verified":false,"followers_count":1,"friends_count":18,"listed_count":0,"favourites_count":1,"statuses_count":7,"created_at":"Tue Nov 03 19:53:22 +0000 2015","utc_offset":null,"time_zone":null,"geo_enabled":false,"lang":"de","contributors_enabled":false,"is_translator":false,"profile_background_color":"C0DEED","profile_background_image_url":"http:\/\/abs.twimg.com\/images\/themes\/theme1\/bg.png","profile_background_image_url_https":"https:\/\/abs.twimg.com\/images\/themes\/theme1\/bg.png","profile_background_tile":false,"profile_link_color":"0084B4","profile_sidebar_border_color":"C0DEED","profile_sidebar_fill_color":"DDEEF6","profile_text_color":"333333","profile_use_background_image":true,"profile_image_url":"http:\/\/abs.twimg.com\/sticky\/default_profile_images\/default_profile_6_normal.png","profile_image_url_https":"https:\/\/abs.twimg.com\/sticky\/default_profile_images\/default_profile_6_normal.png","default_profile":true,"default_profile_image":true,"following":null,"follow_request_sent":null,"notifications":null},"geo":null,"coordinates":null,"place":null,"contributors":null,"retweeted_status":{"created_at":"Sat Jun 04 20:19:49 +0000 2016","id":739189938143498240,"id_str":"739189938143498240","text":"Wie hei\u00dft es so sch\u00f6n:Verpatzte Generalprobe, gelungene Premiere. #autned","source":"\u003ca href=\"http:\/\/twitter.com\/#!\/download\/ipad\" rel=\"nofollow\"\u003eTwitter for iPad\u003c\/a\u003e","truncated":false,"in_reply_to_status_id":null,"in_reply_to_status_id_str":null,"in_reply_to_user_id":null,"in_reply_to_user_id_str":null,"in_reply_to_screen_name":null,"user":{"id":2274329551,"id_str":"2274329551","name":"Christian Neuhold","screen_name":"ChrisNeuhold","location":null,"url":null,"description":"Journalist -  twittert hier Privates und Berufliches","protected":false,"verified":false,"followers_count":1403,"friends_count":546,"listed_count":50,"favourites_count":2261,"statuses_count":7641,"created_at":"Fri Jan 03 10:41:15 +0000 2014","utc_offset":7200,"time_zone":"Vienna","geo_enabled":true,"lang":"de","contributors_enabled":false,"is_translator":false,"profile_background_color":"C0DEED","profile_background_image_url":"http:\/\/abs.twimg.com\/images\/themes\/theme1\/bg.png","profile_background_image_url_https":"https:\/\/abs.twimg.com\/images\/themes\/theme1\/bg.png","profile_background_tile":false,"profile_link_color":"0084B4","profile_sidebar_border_color":"C0DEED","profile_sidebar_fill_color":"DDEEF6","profile_text_color":"333333","profile_use_background_image":true,"profile_image_url":"http:\/\/pbs.twimg.com\/profile_images\/419058383333781504\/9MT_4lSy_normal.jpeg","profile_image_url_https":"https:\/\/pbs.twimg.com\/profile_images\/419058383333781504\/9MT_4lSy_normal.jpeg","profile_banner_url":"https:\/\/pbs.twimg.com\/profile_banners\/2274329551\/1401273074","default_profile":true,"default_profile_image":false,"following":null,"follow_request_sent":null,"notifications":null},"geo":null,"coordinates":null,"place":{"id":"32df474e5c114569","url":"https:\/\/api.twitter.com\/1.1\/geo\/id\/32df474e5c114569.json","place_type":"city","name":"Maissau","full_name":"Maissau, \u00d6sterreich","country_code":"AT","country":"\u00d6sterreich","bounding_box":{"type":"Polygon","coordinates":[[[15.738428,48.534741],[15.738428,48.603742],[15.904872,48.603742],[15.904872,48.534741]]]},"attributes":{}},"contributors":null,"is_quote_status":false,"retweet_count":1,"favorite_count":3,"entities":{"hashtags":[{"text":"autned","indices":[66,73]}],"urls":[],"user_mentions":[],"symbols":[]},"favorited":false,"retweeted":false,"filter_level":"low","lang":"de"},"is_quote_status":false,"retweet_count":0,"favorite_count":0,"entities":{"hashtags":[{"text":"autned","indices":[84,91]}],"urls":[],"user_mentions":[{"screen_name":"ChrisNeuhold","name":"Christian Neuhold","id":2274329551,"id_str":"2274329551","indices":[3,16]}],"symbols":[]},"favorited":false,"retweeted":false,"filter_level":"low","lang":"de","timestamp_ms":"1465071663641"}
{"created_at":"Sat Jun 04 20:21:18 +0000 2016","id":739190312984317956,"id_str":"739190312984317956","text":"Wie konnte sich die #Elftaal nicht f\u00fcr die #EM2016 qualifizieren? Tschechien, Island &amp; die T\u00fcrkei sind nicht gerade die \u00dcbergegner! #AUTNED","source":"\u003ca href=\"http:\/\/twitter.com\/download\/iphone\" rel=\"nofollow\"\u003eTwitter for iPhone\u003c\/a\u003e","truncated":false,"in_reply_to_status_id":null,"in_reply_to_status_id_str":null,"in_reply_to_user_id":null,"in_reply_to_user_id_str":null,"in_reply_to_screen_name":null,"user":{"id":889671680,"id_str":"889671680","name":"Jakob Sebastian Kahl","screen_name":"KahlJakob","location":"Vienna, Austria","url":null,"description":null,"protected":false,"verified":false,"followers_count":197,"friends_count":392,"listed_count":31,"favourites_count":68,"statuses_count":922,"created_at":"Thu Oct 18 20:25:52 +0000 2012","utc_offset":null,"time_zone":null,"geo_enabled":false,"lang":"de","contributors_enabled":false,"is_translator":false,"profile_background_color":"C0DEED","profile_background_image_url":"http:\/\/abs.twimg.com\/images\/themes\/theme1\/bg.png","profile_background_image_url_https":"https:\/\/abs.twimg.com\/images\/themes\/theme1\/bg.png","profile_background_tile":false,"profile_link_color":"0084B4","profile_sidebar_border_color":"C0DEED","profile_sidebar_fill_color":"DDEEF6","profile_text_color":"333333","profile_use_background_image":true,"profile_image_url":"http:\/\/pbs.twimg.com\/profile_images\/3694793883\/311b246bd7018bec7bd69e2e5a59094a_normal.jpeg","profile_image_url_https":"https:\/\/pbs.twimg.com\/profile_images\/3694793883\/311b246bd7018bec7bd69e2e5a59094a_normal.jpeg","default_profile":true,"default_profile_image":false,"following":null,"follow_request_sent":null,"notifications":null},"geo":null,"coordinates":null,"place":null,"contributors":null,"is_quote_status":false,"retweet_count":0,"favorite_count":0,"entities":{"hashtags":[{"text":"Elftaal","indices":[20,28]},{"text":"EM2016","indices":[43,50]},{"text":"AUTNED","indices":[136,143]}],"urls":[],"user_mentions":[],"symbols":[]},"favorited":false,"retweeted":false,"filter_level":"low","lang":"de","timestamp_ms":"1465071678764"}
{"created_at":"Sat Jun 04 20:21:21 +0000 2016","id":739190322371137536,"id_str":"739190322371137536","text":"\"der zug nach vorne war heute noch nicht da\" dahinter die werbung der \u00f6bb zu sehen. ganz mein humor #autned","source":"\u003ca href=\"https:\/\/mobile.twitter.com\" rel=\"nofollow\"\u003eMobile Web (M2)\u003c\/a\u003e","truncated":false,"in_reply_to_status_id":null,"in_reply_to_status_id_str":null,"in_reply_to_user_id":null,"in_reply_to_user_id_str":null,"in_reply_to_screen_name":null,"user":{"id":75239532,"id_str":"75239532","name":"Sophie WB","screen_name":"thesopherl","location":"Graz, Austria","url":null,"description":"my heart goes shalalalala! :D","protected":false,"verified":false,"followers_count":969,"friends_count":955,"listed_count":4,"favourites_count":644,"statuses_count":6847,"created_at":"Fri Sep 18 09:18:23 +0000 2009","utc_offset":10800,"time_zone":"Athens","geo_enabled":false,"lang":"en","contributors_enabled":false,"is_translator":false,"profile_background_color":"709396","profile_background_image_url":"http:\/\/abs.twimg.com\/images\/themes\/theme1\/bg.png","profile_background_image_url_https":"https:\/\/abs.twimg.com\/images\/themes\/theme1\/bg.png","profile_background_tile":false,"profile_link_color":"FF3300","profile_sidebar_border_color":"86A4A6","profile_sidebar_fill_color":"A0C5C7","profile_text_color":"333333","profile_use_background_image":true,"profile_image_url":"http:\/\/pbs.twimg.com\/profile_images\/2905900541\/944a29ef73e906fff0345cb94dc35b54_normal.jpeg","profile_image_url_https":"https:\/\/pbs.twimg.com\/profile_images\/2905900541\/944a29ef73e906fff0345cb94dc35b54_normal.jpeg","default_profile":false,"default_profile_image":false,"following":null,"follow_request_sent":null,"notifications":null},"geo":null,"coordinates":null,"place":null,"contributors":null,"is_quote_status":false,"retweet_count":0,"favorite_count":0,"entities":{"hashtags":[{"text":"autned","indices":[100,107]}],"urls":[],"user_mentions":[],"symbols":[]},"favorited":false,"retweeted":false,"filter_level":"low","lang":"de","timestamp_ms":"1465071681002"}
{"created_at":"Sat Jun 04 20:21:24 +0000 2016","id":739190338393407488,"id_str":"739190338393407488","text":"So und jetzt zur wichtigeren Frage: Morgen: Djoker odere Murray? #AUTNED","source":"\u003ca href=\"http:\/\/twitter.com\" rel=\"nofollow\"\u003eTwitter Web Client\u003c\/a\u003e","truncated":false,"in_reply_to_status_id":null,"in_reply_to_status_id_str":null,"in_reply_to_user_id":null,"in_reply_to_user_id_str":null,"in_reply_to_screen_name":null,"user":{"id":1912438501,"id_str":"1912438501","name":"Marie Samstag","screen_name":"mariesamstag","location":"Wien\/Bucklige Welt","url":null,"description":"Journalistin und Autorin.\r\nPrivate Interessen: Kunst. Kultur. Kulinarik.\r\nMSamstag@gmx.at","protected":false,"verified":false,"followers_count":80,"friends_count":85,"listed_count":2,"favourites_count":42,"statuses_count":131,"created_at":"Fri Sep 27 21:55:49 +0000 2013","utc_offset":7200,"time_zone":"Vienna","geo_enabled":true,"lang":"de","contributors_enabled":false,"is_translator":false,"profile_background_color":"ACDED6","profile_background_image_url":"http:\/\/abs.twimg.com\/images\/themes\/theme18\/bg.gif","profile_background_image_url_https":"https:\/\/abs.twimg.com\/images\/themes\/theme18\/bg.gif","profile_background_tile":true,"profile_link_color":"3B94D9","profile_sidebar_border_color":"000000","profile_sidebar_fill_color":"000000","profile_text_color":"000000","profile_use_background_image":true,"profile_image_url":"http:\/\/pbs.twimg.com\/profile_images\/378800000516422212\/3ee5e274135c041517fd0c353ddd6312_normal.jpeg","profile_image_url_https":"https:\/\/pbs.twimg.com\/profile_images\/378800000516422212\/3ee5e274135c041517fd0c353ddd6312_normal.jpeg","profile_banner_url":"https:\/\/pbs.twimg.com\/profile_banners\/1912438501\/1440082401","default_profile":false,"default_profile_image":false,"following":null,"follow_request_sent":null,"notifications":null},"geo":null,"coordinates":null,"place":null,"contributors":null,"is_quote_status":false,"retweet_count":0,"favorite_count":0,"entities":{"hashtags":[{"text":"AUTNED","indices":[65,72]}],"urls":[],"user_mentions":[],"symbols":[]},"favorited":false,"retweeted":false,"filter_level":"low","lang":"de","timestamp_ms":"1465071684822"}
{"created_at":"Sat Jun 04 20:21:25 +0000 2016","id":739190340905762816,"id_str":"739190340905762816","text":"Ich sag einmal so: der Kas is g'essn bzw. die Messe ist gelesen.  Da wie dort.  #autned #katzenberger","source":"\u003ca href=\"https:\/\/about.twitter.com\/products\/tweetdeck\" rel=\"nofollow\"\u003eTweetDeck\u003c\/a\u003e","truncated":false,"in_reply_to_status_id":null,"in_reply_to_status_id_str":null,"in_reply_to_user_id":null,"in_reply_to_user_id_str":null,"in_reply_to_screen_name":null,"user":{"id":173815196,"id_str":"173815196","name":"wuchale","screen_name":"wuchale","location":"Wienerwald ","url":null,"description":"EdelgrantlerPauschalisierungsgegnerKann auch ganz anders","protected":false,"verified":false,"followers_count":1538,"friends_count":783,"listed_count":68,"favourites_count":32653,"statuses_count":12525,"created_at":"Mon Aug 02 12:35:10 +0000 2010","utc_offset":-7200,"time_zone":"Greenland","geo_enabled":false,"lang":"de","contributors_enabled":false,"is_translator":false,"profile_background_color":"ACDED6","profile_background_image_url":"http:\/\/pbs.twimg.com\/profile_background_images\/176706469\/IMG_1881-1.JPG","profile_background_image_url_https":"https:\/\/pbs.twimg.com\/profile_background_images\/176706469\/IMG_1881-1.JPG","profile_background_tile":false,"profile_link_color":"4A913C","profile_sidebar_border_color":"EEEEEE","profile_sidebar_fill_color":"F6F6F6","profile_text_color":"333333","profile_use_background_image":true,"profile_image_url":"http:\/\/pbs.twimg.com\/profile_images\/737741101298122752\/faW7ldaI_normal.jpg","profile_image_url_https":"https:\/\/pbs.twimg.com\/profile_images\/737741101298122752\/faW7ldaI_normal.jpg","profile_banner_url":"https:\/\/pbs.twimg.com\/profile_banners\/173815196\/1464726501","default_profile":false,"default_profile_image":false,"following":null,"follow_request_sent":null,"notifications":null},"geo":null,"coordinates":null,"place":null,"contributors":null,"is_quote_status":false,"retweet_count":0,"favorite_count":0,"entities":{"hashtags":[{"text":"autned","indices":[80,87]},{"text":"katzenberger","indices":[88,101]}],"urls":[],"user_mentions":[],"symbols":[]},"favorited":false,"retweeted":false,"filter_level":"low","lang":"de","timestamp_ms":"1465071685421"}
{"created_at":"Sat Jun 04 20:21:38 +0000 2016","id":739190395238817792,"id_str":"739190395238817792","text":"RT @rprazak: Die ersten \"Fans\" gehen schon. #autned","source":"\u003ca href=\"http:\/\/twitter.com\/download\/android\" rel=\"nofollow\"\u003eTwitter for Android\u003c\/a\u003e","truncated":false,"in_reply_to_status_id":null,"in_reply_to_status_id_str":null,"in_reply_to_user_id":null,"in_reply_to_user_id_str":null,"in_reply_to_screen_name":null,"user":{"id":3246755997,"id_str":"3246755997","name":"T-hailand\u2122\u00a9 Marius","screen_name":"TvJunkieTotal","location":"In einem Europa ohne Grenzen","url":null,"description":"...und das sage ich jetzt nicht \nnur weil ich betrunken bin!","protected":false,"verified":false,"followers_count":1088,"friends_count":4487,"listed_count":14,"favourites_count":3230,"statuses_count":3379,"created_at":"Mon May 11 21:03:11 +0000 2015","utc_offset":null,"time_zone":null,"geo_enabled":false,"lang":"de","contributors_enabled":false,"is_translator":false,"profile_background_color":"C0DEED","profile_background_image_url":"http:\/\/abs.twimg.com\/images\/themes\/theme1\/bg.png","profile_background_image_url_https":"https:\/\/abs.twimg.com\/images\/themes\/theme1\/bg.png","profile_background_tile":false,"profile_link_color":"0084B4","profile_sidebar_border_color":"C0DEED","profile_sidebar_fill_color":"DDEEF6","profile_text_color":"333333","profile_use_background_image":true,"profile_image_url":"http:\/\/pbs.twimg.com\/profile_images\/692983506704670720\/nEBw379-_normal.jpg","profile_image_url_https":"https:\/\/pbs.twimg.com\/profile_images\/692983506704670720\/nEBw379-_normal.jpg","profile_banner_url":"https:\/\/pbs.twimg.com\/profile_banners\/3246755997\/1454055231","default_profile":true,"default_profile_image":false,"following":null,"follow_request_sent":null,"notifications":null},"geo":null,"coordinates":null,"place":null,"contributors":null,"retweeted_status":{"created_at":"Sat Jun 04 20:18:40 +0000 2016","id":739189650150051841,"id_str":"739189650150051841","text":"Die ersten \"Fans\" gehen schon. #autned","source":"\u003ca href=\"http:\/\/twitter.com\/#!\/download\/ipad\" rel=\"nofollow\"\u003eTwitter for iPad\u003c\/a\u003e","truncated":false,"in_reply_to_status_id":null,"in_reply_to_status_id_str":null,"in_reply_to_user_id":null,"in_reply_to_user_id_str":null,"in_reply_to_screen_name":null,"user":{"id":80853208,"id_str":"80853208","name":"Robert Prazak","screen_name":"rprazak","location":"M\u00f6dling \/ Wien","url":"http:\/\/www.prazak.at","description":"Journalist, Schreiber - oder so. http:\/\/about.me\/RobertPrazak http:\/\/www.prazak.at http:\/\/www.techzoom.at","protected":false,"verified":false,"followers_count":785,"friends_count":782,"listed_count":66,"favourites_count":7524,"statuses_count":8720,"created_at":"Thu Oct 08 13:53:39 +0000 2009","utc_offset":7200,"time_zone":"Vienna","geo_enabled":true,"lang":"de","contributors_enabled":false,"is_translator":false,"profile_background_color":"131516","profile_background_image_url":"http:\/\/pbs.twimg.com\/profile_background_images\/378800000153523484\/04_wc_oi.jpeg","profile_background_image_url_https":"https:\/\/pbs.twimg.com\/profile_background_images\/378800000153523484\/04_wc_oi.jpeg","profile_background_tile":false,"profile_link_color":"1A1C1C","profile_sidebar_border_color":"000000","profile_sidebar_fill_color":"EFEFEF","profile_text_color":"333333","profile_use_background_image":true,"profile_image_url":"http:\/\/pbs.twimg.com\/profile_images\/557950862564147202\/ziAj_1rL_normal.jpeg","profile_image_url_https":"https:\/\/pbs.twimg.com\/profile_images\/557950862564147202\/ziAj_1rL_normal.jpeg","profile_banner_url":"https:\/\/pbs.twimg.com\/profile_banners\/80853208\/1459859148","default_profile":false,"default_profile_image":false,"following":null,"follow_request_sent":null,"notifications":null},"geo":null,"coordinates":null,"place":null,"contributors":null,"is_quote_status":false,"retweet_count":2,"favorite_count":4,"entities":{"hashtags":[{"text":"autned","indices":[31,38]}],"urls":[],"user_mentions":[],"symbols":[]},"favorited":false,"retweeted":false,"filter_level":"low","lang":"de"},"is_quote_status":false,"retweet_count":0,"favorite_count":0,"entities":{"hashtags":[{"text":"autned","indices":[44,51]}],"urls":[],"user_mentions":[{"screen_name":"rprazak","name":"Robert Prazak","id":80853208,"id_str":"80853208","indices":[3,11]}],"symbols":[]},"favorited":false,"retweeted":false,"filter_level":"low","lang":"de","timestamp_ms":"1465071698375"}
{"created_at":"Sat Jun 04 20:21:40 +0000 2016","id":739190404571107328,"id_str":"739190404571107328","text":"ERFOLGSFANS!!!!!!! \ud83d\ude20\ud83d\ude20\ud83d\ude20\ud83d\ude20 #AUTNED","source":"\u003ca href=\"http:\/\/twitter.com\/download\/android\" rel=\"nofollow\"\u003eTwitter for Android\u003c\/a\u003e","truncated":false,"in_reply_to_status_id":null,"in_reply_to_status_id_str":null,"in_reply_to_user_id":null,"in_reply_to_user_id_str":null,"in_reply_to_screen_name":null,"user":{"id":1471284732,"id_str":"1471284732","name":"Steve Zinnagl","screen_name":"SZinnagl","location":"Stockerau","url":null,"description":"musiclover; firefighter; audidriver; ITTechnician, hobbyDJ, Paramedic, Petrolhead, @skrapid, @redbullracing","protected":false,"verified":false,"followers_count":59,"friends_count":251,"listed_count":2,"favourites_count":570,"statuses_count":1462,"created_at":"Fri May 31 04:22:15 +0000 2013","utc_offset":7200,"time_zone":"Vienna","geo_enabled":true,"lang":"de","contributors_enabled":false,"is_translator":false,"profile_background_color":"000000","profile_background_image_url":"http:\/\/abs.twimg.com\/images\/themes\/theme14\/bg.gif","profile_background_image_url_https":"https:\/\/abs.twimg.com\/images\/themes\/theme14\/bg.gif","profile_background_tile":false,"profile_link_color":"FF9900","profile_sidebar_border_color":"000000","profile_sidebar_fill_color":"000000","profile_text_color":"000000","profile_use_background_image":false,"profile_image_url":"http:\/\/pbs.twimg.com\/profile_images\/722139263727464448\/3iMHmjzJ_normal.jpg","profile_image_url_https":"https:\/\/pbs.twimg.com\/profile_images\/722139263727464448\/3iMHmjzJ_normal.jpg","profile_banner_url":"https:\/\/pbs.twimg.com\/profile_banners\/1471284732\/1447798503","default_profile":false,"default_profile_image":false,"following":null,"follow_request_sent":null,"notifications":null},"geo":null,"coordinates":null,"place":{"id":"f8d1b840d29262d4","url":"https:\/\/api.twitter.com\/1.1\/geo\/id\/f8d1b840d29262d4.json","place_type":"city","name":"Stockerau","full_name":"Stockerau, \u00d6sterreich","country_code":"AT","country":"\u00d6sterreich","bounding_box":{"type":"Polygon","coordinates":[[[16.138329,48.352683],[16.138329,48.421546],[16.253124,48.421546],[16.253124,48.352683]]]},"attributes":{}},"contributors":null,"is_quote_status":false,"retweet_count":0,"favorite_count":0,"entities":{"hashtags":[{"text":"AUTNED","indices":[24,31]}],"urls":[],"user_mentions":[],"symbols":[]},"favorited":false,"retweeted":false,"filter_level":"low","lang":"de","timestamp_ms":"1465071700600"}
{"created_at":"Sat Jun 04 20:21:46 +0000 2016","id":739190429145534465,"id_str":"739190429145534465","text":"Wunder sollen angeblich immer wieder passieren. Beim Polzer braucht es halt l\u00e4nger. #AUTNED","source":"\u003ca href=\"http:\/\/twitter.com\/download\/iphone\" rel=\"nofollow\"\u003eTwitter for iPhone\u003c\/a\u003e","truncated":false,"in_reply_to_status_id":null,"in_reply_to_status_id_str":null,"in_reply_to_user_id":null,"in_reply_to_user_id_str":null,"in_reply_to_screen_name":null,"user":{"id":724865365784801282,"id_str":"724865365784801282","name":"Raffaela Versa","screen_name":"DieRaffa","location":"Wien, \u00d6sterreich","url":null,"description":"| Keine Journalistin oder Bloggerin, daf\u00fcr aber HRMin & Chefin im Hintergrund; nebenbei Studentin | Zwitschert \u00fcber Politik & das \u00dcberleben im Alltag |","protected":false,"verified":false,"followers_count":17,"friends_count":64,"listed_count":2,"favourites_count":104,"statuses_count":55,"created_at":"Tue Apr 26 07:39:05 +0000 2016","utc_offset":-25200,"time_zone":"Pacific Time (US & Canada)","geo_enabled":false,"lang":"de","contributors_enabled":false,"is_translator":false,"profile_background_color":"ABB8C2","profile_background_image_url":"http:\/\/pbs.twimg.com\/profile_background_images\/724875695344766976\/FoO7VyOp.jpg","profile_background_image_url_https":"https:\/\/pbs.twimg.com\/profile_background_images\/724875695344766976\/FoO7VyOp.jpg","profile_background_tile":false,"profile_link_color":"ABB8C2","profile_sidebar_border_color":"000000","profile_sidebar_fill_color":"000000","profile_text_color":"000000","profile_use_background_image":false,"profile_image_url":"http:\/\/pbs.twimg.com\/profile_images\/729399301793828864\/SNk3gbxI_normal.jpg","profile_image_url_https":"https:\/\/pbs.twimg.com\/profile_images\/729399301793828864\/SNk3gbxI_normal.jpg","profile_banner_url":"https:\/\/pbs.twimg.com\/profile_banners\/724865365784801282\/1461660731","default_profile":false,"default_profile_image":false,"following":null,"follow_request_sent":null,"notifications":null},"geo":null,"coordinates":null,"place":null,"contributors":null,"is_quote_status":false,"retweet_count":0,"favorite_count":0,"entities":{"hashtags":[{"text":"AUTNED","indices":[84,91]}],"urls":[],"user_mentions":[],"symbols":[]},"favorited":false,"retweeted":false,"filter_level":"low","lang":"de","timestamp_ms":"1465071706459"}
{"created_at":"Sat Jun 04 20:21:48 +0000 2016","id":739190437358010370,"id_str":"739190437358010370","text":"F\u00fcr Julian Baumgartlinger kommt Stefan Ilsanker. (90.) 0:2 #autned","source":"\u003ca href=\"http:\/\/twitter.com\" rel=\"nofollow\"\u003eTwitter Web Client\u003c\/a\u003e","truncated":false,"in_reply_to_status_id":null,"in_reply_to_status_id_str":null,"in_reply_to_user_id":null,"in_reply_to_user_id_str":null,"in_reply_to_screen_name":null,"user":{"id":53078727,"id_str":"53078727","name":"\u00d6FB - oefb.at","screen_name":"oefb1904","location":"Wien - \u00d6sterreich","url":"http:\/\/www.oefb.at","description":"Der \u00d6sterreichische Fu\u00dfball-Bund twittert","protected":false,"verified":true,"followers_count":20555,"friends_count":220,"listed_count":303,"favourites_count":1219,"statuses_count":6819,"created_at":"Thu Jul 02 14:35:13 +0000 2009","utc_offset":7200,"time_zone":"Vienna","geo_enabled":true,"lang":"de","contributors_enabled":false,"is_translator":false,"profile_background_color":"F7FBFC","profile_background_image_url":"http:\/\/pbs.twimg.com\/profile_background_images\/622396356\/yf8ahw9t0vapv2wjf2je.jpeg","profile_background_image_url_https":"https:\/\/pbs.twimg.com\/profile_background_images\/622396356\/yf8ahw9t0vapv2wjf2je.jpeg","profile_background_tile":false,"profile_link_color":"0F0105","profile_sidebar_border_color":"0A010A","profile_sidebar_fill_color":"EB1123","profile_text_color":"333333","profile_use_background_image":true,"profile_image_url":"http:\/\/pbs.twimg.com\/profile_images\/634723902921424896\/SajKVKmE_normal.png","profile_image_url_https":"https:\/\/pbs.twimg.com\/profile_images\/634723902921424896\/SajKVKmE_normal.png","profile_banner_url":"https:\/\/pbs.twimg.com\/profile_banners\/53078727\/1460363940","default_profile":false,"default_profile_image":false,"following":null,"follow_request_sent":null,"notifications":null},"geo":null,"coordinates":null,"place":null,"contributors":null,"is_quote_status":false,"retweet_count":0,"favorite_count":0,"entities":{"hashtags":[{"text":"autned","indices":[59,66]}],"urls":[],"user_mentions":[],"symbols":[]},"favorited":false,"retweeted":false,"filter_level":"low","lang":"de","timestamp_ms":"1465071708417"}

{"created_at":"Sat Jun 04 20:21:55 +0000 2016","id":739190468303552512,"id_str":"739190468303552512","text":"Ein bissl Luft nach oben w\u00e4re noch. ;) #autned #euro","source":"\u003ca href=\"http:\/\/twitter.com\/download\/iphone\" rel=\"nofollow\"\u003eTwitter for iPhone\u003c\/a\u003e","truncated":false,"in_reply_to_status_id":null,"in_reply_to_status_id_str":null,"in_reply_to_user_id":null,"in_reply_to_user_id_str":null,"in_reply_to_screen_name":null,"user":{"id":273631032,"id_str":"273631032","name":"Sabine Karrer","screen_name":"FrauKassandra","location":"Vienna","url":"http:\/\/sabinekarrer.at","description":"Schreibt. Liest. Diskutiert. Fotografiert. Liebt Wien. Bei\u00dft im Normalfall nicht. Alles hier ist sowas von privat. Es ist gar nicht so kompliziert. ;-)","protected":false,"verified":false,"followers_count":1699,"friends_count":1551,"listed_count":83,"favourites_count":27209,"statuses_count":56590,"created_at":"Mon Mar 28 21:30:32 +0000 2011","utc_offset":-7200,"time_zone":"Greenland","geo_enabled":false,"lang":"de","contributors_enabled":false,"is_translator":false,"profile_background_color":"C0DEED","profile_background_image_url":"http:\/\/abs.twimg.com\/images\/themes\/theme1\/bg.png","profile_background_image_url_https":"https:\/\/abs.twimg.com\/images\/themes\/theme1\/bg.png","profile_background_tile":false,"profile_link_color":"0084B4","profile_sidebar_border_color":"C0DEED","profile_sidebar_fill_color":"DDEEF6","profile_text_color":"333333","profile_use_background_image":true,"profile_image_url":"http:\/\/pbs.twimg.com\/profile_images\/737229302354313217\/a6EOL1sT_normal.jpg","profile_image_url_https":"https:\/\/pbs.twimg.com\/profile_images\/737229302354313217\/a6EOL1sT_normal.jpg","profile_banner_url":"https:\/\/pbs.twimg.com\/profile_banners\/273631032\/1461668281","default_profile":true,"default_profile_image":false,"following":null,"follow_request_sent":null,"notifications":null},"geo":null,"coordinates":null,"place":null,"contributors":null,"is_quote_status":false,"retweet_count":0,"favorite_count":0,"entities":{"hashtags":[{"text":"autned","indices":[39,46]},{"text":"euro","indices":[47,52]}],"urls":[],"user_mentions":[],"symbols":[]},"favorited":false,"retweeted":false,"filter_level":"low","lang":"de","timestamp_ms":"1465071715795"}
{"created_at":"Sat Jun 04 20:21:57 +0000 2016","id":739190474133622785,"id_str":"739190474133622785","text":"90. Ilsanker kommt f\u00fcr Baumgartlinger. Wozu? #autned","source":"\u003ca href=\"https:\/\/about.twitter.com\/products\/tweetdeck\" rel=\"nofollow\"\u003eTweetDeck\u003c\/a\u003e","truncated":false,"in_reply_to_status_id":null,"in_reply_to_status_id_str":null,"in_reply_to_user_id":null,"in_reply_to_user_id_str":null,"in_reply_to_screen_name":null,"user":{"id":1233661152,"id_str":"1233661152","name":"der_rossmann","screen_name":"der_rossmann","location":null,"url":null,"description":"Schlosser, ehem. freier Redakteur, ehem. Hrsg., ehem. CR, Student, Werbeagentur, irgendwas mit Medien | Tweeter vom @WolfsbergerAC | Snapchatter: daniele_rosso","protected":false,"verified":false,"followers_count":566,"friends_count":449,"listed_count":16,"favourites_count":5781,"statuses_count":11642,"created_at":"Sat Mar 02 08:50:30 +0000 2013","utc_offset":null,"time_zone":null,"geo_enabled":false,"lang":"de","contributors_enabled":false,"is_translator":false,"profile_background_color":"C0DEED","profile_background_image_url":"http:\/\/abs.twimg.com\/images\/themes\/theme1\/bg.png","profile_background_image_url_https":"https:\/\/abs.twimg.com\/images\/themes\/theme1\/bg.png","profile_background_tile":false,"profile_link_color":"0084B4","profile_sidebar_border_color":"C0DEED","profile_sidebar_fill_color":"DDEEF6","profile_text_color":"333333","profile_use_background_image":true,"profile_image_url":"http:\/\/pbs.twimg.com\/profile_images\/733346757560705025\/bzbTXRII_normal.jpg","profile_image_url_https":"https:\/\/pbs.twimg.com\/profile_images\/733346757560705025\/bzbTXRII_normal.jpg","profile_banner_url":"https:\/\/pbs.twimg.com\/profile_banners\/1233661152\/1444163442","default_profile":true,"default_profile_image":false,"following":null,"follow_request_sent":null,"notifications":null},"geo":null,"coordinates":null,"place":null,"contributors":null,"is_quote_status":false,"retweet_count":0,"favorite_count":0,"entities":{"hashtags":[{"text":"autned","indices":[45,52]}],"urls":[],"user_mentions":[],"symbols":[]},"favorited":false,"retweeted":false,"filter_level":"low","lang":"de","timestamp_ms":"1465071717185"}
{"created_at":"Sat Jun 04 20:21:58 +0000 2016","id":739190479120683008,"id_str":"739190479120683008","text":"Ich hoffe auf die morgige Wahlkartenausz\u00e4hlung. #AUTNED","source":"\u003ca href=\"http:\/\/twitter.com\/download\/iphone\" rel=\"nofollow\"\u003eTwitter for iPhone\u003c\/a\u003e","truncated":false,"in_reply_to_status_id":null,"in_reply_to_status_id_str":null,"in_reply_to_user_id":null,"in_reply_to_user_id_str":null,"in_reply_to_screen_name":null,"user":{"id":20062208,"id_str":"20062208","name":"Michi Reichelt","screen_name":"mir70","location":"Vienna, Austria","url":"http:\/\/www.seitenblicke.at","description":"Online. Journalist. Chef. Redakteur.","protected":false,"verified":false,"followers_count":668,"friends_count":962,"listed_count":18,"favourites_count":11053,"statuses_count":9731,"created_at":"Wed Feb 04 15:43:16 +0000 2009","utc_offset":7200,"time_zone":"Vienna","geo_enabled":false,"lang":"en","contributors_enabled":false,"is_translator":false,"profile_background_color":"C0DEED","profile_background_image_url":"http:\/\/abs.twimg.com\/images\/themes\/theme1\/bg.png","profile_background_image_url_https":"https:\/\/abs.twimg.com\/images\/themes\/theme1\/bg.png","profile_background_tile":false,"profile_link_color":"0084B4","profile_sidebar_border_color":"C0DEED","profile_sidebar_fill_color":"DDEEF6","profile_text_color":"333333","profile_use_background_image":true,"profile_image_url":"http:\/\/pbs.twimg.com\/profile_images\/663660999556378624\/U4ndyHGJ_normal.jpg","profile_image_url_https":"https:\/\/pbs.twimg.com\/profile_images\/663660999556378624\/U4ndyHGJ_normal.jpg","default_profile":true,"default_profile_image":false,"following":null,"follow_request_sent":null,"notifications":null},"geo":null,"coordinates":null,"place":null,"contributors":null,"is_quote_status":false,"retweet_count":0,"favorite_count":0,"entities":{"hashtags":[{"text":"AUTNED","indices":[48,55]}],"urls":[],"user_mentions":[],"symbols":[]},"favorited":false,"retweeted":false,"filter_level":"low","lang":"de","timestamp_ms":"1465071718374"}
{"created_at":"Sat Jun 04 20:21:59 +0000 2016","id":739190481897279491,"id_str":"739190481897279491","text":"konnte jetzt gem\u00fctlich neben #AUTNED den Blogeintrag zum Film #MoneyMonster vorschreiben, der dann morgen Vormittag online geht.","source":"\u003ca href=\"http:\/\/twitter.com\" rel=\"nofollow\"\u003eTwitter Web Client\u003c\/a\u003e","truncated":false,"in_reply_to_status_id":null,"in_reply_to_status_id_str":null,"in_reply_to_user_id":null,"in_reply_to_user_id_str":null,"in_reply_to_screen_name":null,"user":{"id":475153071,"id_str":"475153071","name":"DaTommy","screen_name":"plapperblog","location":"wien - vienna","url":"http:\/\/derplapperblog.wordpress.com","description":"(Hobby)Film- und Serienblogger - Superhelden-Filmfan - Fan der Indiana Pacers der Blazers u der NBA - Fan von Austria Wien\/BVB\/Benfica - Tweets \u00fcber meine Abeit","protected":false,"verified":false,"followers_count":620,"friends_count":1579,"listed_count":44,"favourites_count":9691,"statuses_count":37502,"created_at":"Thu Jan 26 19:02:13 +0000 2012","utc_offset":7200,"time_zone":"Amsterdam","geo_enabled":true,"lang":"de","contributors_enabled":false,"is_translator":false,"profile_background_color":"C0DEED","profile_background_image_url":"http:\/\/pbs.twimg.com\/profile_background_images\/378800000014520315\/9c660460c646abdac9cb5b90c7a3fd03.jpeg","profile_background_image_url_https":"https:\/\/pbs.twimg.com\/profile_background_images\/378800000014520315\/9c660460c646abdac9cb5b90c7a3fd03.jpeg","profile_background_tile":true,"profile_link_color":"0084B4","profile_sidebar_border_color":"FFFFFF","profile_sidebar_fill_color":"DDEEF6","profile_text_color":"333333","profile_use_background_image":true,"profile_image_url":"http:\/\/pbs.twimg.com\/profile_images\/730787066146111488\/3i3VLVCf_normal.jpg","profile_image_url_https":"https:\/\/pbs.twimg.com\/profile_images\/730787066146111488\/3i3VLVCf_normal.jpg","profile_banner_url":"https:\/\/pbs.twimg.com\/profile_banners\/475153071\/1463068263","default_profile":false,"default_profile_image":false,"following":null,"follow_request_sent":null,"notifications":null},"geo":null,"coordinates":null,"place":null,"contributors":null,"is_quote_status":false,"retweet_count":0,"favorite_count":0,"entities":{"hashtags":[{"text":"AUTNED","indices":[29,36]},{"text":"MoneyMonster","indices":[62,75]}],"urls":[],"user_mentions":[],"symbols":[]},"favorited":false,"retweeted":false,"filter_level":"low","lang":"de","timestamp_ms":"1465071719036"}
